infinistore/test_infinistore.py
infinistore/_infinistore.cpython-312-x86_64-linux-gnu.so
infinistore/__init__.py
infinistore/conftest.py
infinistore/benchmark.py
infinistore/lib.py
infinistore/server.py
infinistore.libs/libuv-671cb6af.so.1.0.0
infinistore-0.2.35.dist-info/entry_points.txt
infinistore-0.2.35.dist-info/RECORD
infinistore-0.2.35.dist-info/METADATA
infinistore-0.2.35.dist-info/top_level.txt
infinistore-0.2.35.dist-info/WHEEL
infinistore-0.2.35.dist-info/LICENSE
