Metadata-Version: 2.1
Name: infinistore
Version: 0.2.35
Summary: A kvcache memory pool
Home-page: https://github.com/bd-iaas-us/infiniStore
License-File: LICENSE
Requires-Dist: torch
Requires-Dist: uvloop
Requires-Dist: fastapi
Requires-Dist: pybind11
Requires-Dist: uvicorn
Requires-Dist: numpy
